kindplay/__init__.py
kindplay/cli.py
kindplay/helm.py
kindplay/kind.py
kindplay/tools.py
kindplay-0.0.3.dist-info/METADATA
kindplay-0.0.3.dist-info/WHEEL
kindplay-0.0.3.dist-info/entry_points.txt
kindplay-0.0.3.dist-info/top_level.txt
kindplay-0.0.3.dist-info/RECORD
