Metadata-Version: 2.1
Name: kindplay
Version: 0.0.3
Summary: Kind playground cli
Home-page: https://github.com/tchelovilar/kindplay
Author: Marcelo Silveira Vilar
Author-email: tchelovilar@gmail.com
License: GPLv3+
Project-URL: Bug Tracker, https://github.com/tchelovilar/kindplay/issues
Project-URL: Source Code, https://github.com/tchelovilar/kindplay
Classifier: Programming Language :: Python :: 3
Classifier: License :: OSI Approved :: GNU General Public License v3 or later (GPLv3+)
Classifier: Operating System :: OS Independent
Requires-Dist: pyyaml (==5.4.1)
Requires-Dist: argparse (==1.4.0)
Requires-Dist: kubernetes (>=23.6.0)
